{
    "pb":{
        "key":"pelyr",
        "value":"0_2",
        "active":true,
        "remark":"PB范围" 
    },
    "pettm":{
        "key":"pettm",
        "value":"0_20",
        "active":true,
        "remark":"TTM范围"
    },
    "pelyr":{
        "key":"pelyr",
        "value":"0_20",
        "active":true,
        "remark":"LYR范围"
    },
    "order_by":{
        "key":"order_by",
        "value":"pb",
        "active":true,
        "remark":"按什么类别排序"
    },
    "order":{
        "key":"pelyr",
        "value":"asc",
        "active":true,
        "remark":"排序规则。asc为升序，desc为降序"
    },
    "size":{
        "key":"size",
        "value":50,
        "active":true,
        "remark":"返回数据条数"
    },
    "category":{
        "key":"category",
        "value":"CN",
        "active":true,
        "remark":"投资市场。CN表示为A股"
    }, 
    "exchange":{
        "key":"exchange",
        "value":"sh_sz",
        "active":true,
        "remark":"交易所。sh_sz表示上证和深证"
    },
    "only_count":{
        "key":"only_count",
        "value":0,
        "active":true,
        "remark":"未知。必备"
    }
}